Metadata-Version: 2.1
Name: pulumi-teamcity
Version: 0.0.16
Home-page: https://github.com/oss4u/
License: Apache-2.0
Project-URL: Repository, https://github.com/oss4u/pulumi-teamcity-native
Requires-Python: >=3.8
